byted_data_watch/__init__.py
byted_data_watch-0.0.1.dist-info/METADATA
byted_data_watch-0.0.1.dist-info/WHEEL
byted_data_watch-0.0.1.dist-info/top_level.txt
byted_data_watch-0.0.1.dist-info/RECORD
