Metadata-Version: 2.1
Name: byted-data-watch
Version: 0.0.1
Summary: A simple package named byted_data_watch
Home-page: https://github.com/artifact/byted_data_watch.git
Author: artifact
Author-email: artifact@example.com
License: UNKNOWN
Platform: UNKNOWN
Classifier: Programming Language :: Python :: 3
Classifier: License :: OSI Approved :: MIT License
Classifier: Operating System :: OS Independent
